privacera_shield_common/__init__.py
privacera_shield_common/async_base_rest_http_client.py
privacera_shield_common/async_http_transport.py
privacera_shield_common/audit_spooler.py
privacera_shield_common/config_utils.py
privacera_shield_common/constants.py
privacera_shield_common/encryption.py
privacera_shield_common/file_utils.py
privacera_shield_common/http_transport.py
privacera_shield_common/lru_cache.py
privacera_shield_common/paig_exception.py
privacera_shield_common/rbac_manager.py
privacera_shield_common/response.py
privacera_shield_common/otel/__init__.py
privacera_shield_common/otel/metrics/__init__.py
privacera_shield_common/otel/metrics/custom_metrics_manager.py
privacera_shield_common/otel/metrics/fastapi_metrics_manager.py
privacera_shield_common/otel/metrics/lru_cache_metrics_manager.py
privacera_shield_common/otel/utils/__init__.py
privacera_shield_common/otel/utils/logging_handler.py
privacera_shield_common/otel/utils/pyroscope_collector.py
privacera_shield_common/otel/utils/tracing_executor.py
privacera_shield_common-1.5.0.dist-info/METADATA
privacera_shield_common-1.5.0.dist-info/WHEEL
privacera_shield_common-1.5.0.dist-info/licenses/LICENSE
privacera_shield_common-1.5.0.dist-info/RECORD
